Metadata-Version: 2.1
Name: ucplots
Version: 0.2.0
Summary: A simple package for plotting unit cells
Author: Rajesh Nakka
Author-email: 338rajesh@gmail.com
Classifier: Programming Language :: Python :: 3
Classifier: License :: OSI Approved :: MIT License
Classifier: Operating System :: OS Independent
Requires-Python: >=3.9
License-File: LICENSE
